djangoldp_custom_dfc/__init__.py
djangoldp_custom_dfc/admin.py
djangoldp_custom_dfc/apps.py
djangoldp_custom_dfc/djangoldp_urls.py
djangoldp_custom_dfc/views.py
djangoldp_custom_dfc/migrations/0001_initial.py
djangoldp_custom_dfc/migrations/0002_remove_enterpriseextension_services_delete_service.py
djangoldp_custom_dfc/migrations/__init__.py
djangoldp_custom_dfc/models/__base.py
djangoldp_custom_dfc/models/__init__.py
djangoldp_custom_dfc/models/enterprise_extension.py
djangoldp_custom_dfc-1.0.4.dist-info/METADATA
djangoldp_custom_dfc-1.0.4.dist-info/WHEEL
djangoldp_custom_dfc-1.0.4.dist-info/top_level.txt
djangoldp_custom_dfc-1.0.4.dist-info/RECORD
