Metadata-Version: 2.1
Name: djangoldp-custom-dfc
Version: 1.0.4
Summary: djangoldp package for Custom DFC (CQCM)
Home-page: https://git.startinblox.com/djangoldp-packages/djangoldp-custom-dfc
Author: Startinblox
Author-email: jbaptiste@startinblox.com
License: MIT
Classifier: Programming Language :: Python :: 3
Requires-Dist: djangoldp~=4.0.0
Requires-Dist: djangoldp-data-food-consortium
Provides-Extra: include_package_data
Requires-Dist: True; extra == "include-package-data"
